file_chunk_iterators/__init__.py
file_chunk_iterators/file_chunk_iterators.py
file_chunk_iterators-0.0.1.dist-info/LICENSE
file_chunk_iterators-0.0.1.dist-info/METADATA
file_chunk_iterators-0.0.1.dist-info/WHEEL
file_chunk_iterators-0.0.1.dist-info/top_level.txt
file_chunk_iterators-0.0.1.dist-info/RECORD
