Metadata-Version: 2.1
Name: file-chunk-iterators
Version: 0.0.1
Summary: Python classes to iterate through files in chunks
Home-page: https://github.com/pypa/sampleproject
Author: Marco Mariotti
Author-email: marco.mariotti@ub.edu
Classifier: Programming Language :: Python :: 3
Classifier: License :: OSI Approved :: MIT License
Classifier: Operating System :: OS Independent
Requires-Python: >=3.6
License-File: LICENSE
